{
    "ThunderSearch": {
        "checkpoints": [
            {
                "steps": 499909,
                "file_path": "results\\Run3\\ThunderSearch\\ThunderSearch-499909.onnx",
                "reward": -6.040605776237719,
                "creation_time": 1746905573.378588,
                "auxillary_file_paths": [
                    "results\\Run3\\ThunderSearch\\ThunderSearch-499909.pt"
                ]
            },
            {
                "steps": 543868,
                "file_path": "results\\Run3\\ThunderSearch\\ThunderSearch-543868.onnx",
                "reward": -7.14649330756881,
                "creation_time": 1746905669.7083368,
                "auxillary_file_paths": [
                    "results\\Run3\\ThunderSearch\\ThunderSearch-543868.pt"
                ]
            }
        ],
        "final_checkpoint": {
            "steps": 543868,
            "file_path": "results\\Run3\\ThunderSearch.onnx",
            "reward": -7.14649330756881,
            "creation_time": 1746905669.7083368,
            "auxillary_file_paths": [
                "results\\Run3\\ThunderSearch\\ThunderSearch-543868.pt"
            ]
        }
    },
    "metadata": {
        "stats_format_version": "0.3.0",
        "mlagents_version": "0.28.0",
        "torch_version": "1.7.1+cu110"
    }
}